firelink/__init__.py
firelink/_version.py
firelink/fire.py
firelink/logger.py
firelink/pandas_transform.py
firelink/pipeline.py
firelink/replace.py
firelink/spark_transform.py
firelink/transform.py
firelink-0.1.2.dist-info/LICENSE
firelink-0.1.2.dist-info/METADATA
firelink-0.1.2.dist-info/WHEEL
firelink-0.1.2.dist-info/top_level.txt
firelink-0.1.2.dist-info/RECORD
