Metadata-Version: 2.1
Name: firelink
Version: 0.1.2
Summary: Firelink is based on scikit-learn pipeline and adding the functionality to store the pipeline in `.yaml` or `.ember` file for production.
Author: Chengran (Owen) Ouyang
Author-email: chengranouyang@gmail.com
License: Apache License
Keywords: firelink documentation tutorial
Platform: UNKNOWN
License-File: LICENSE
Requires-Dist: pandas
Requires-Dist: scikit-learn
Requires-Dist: numpy
